kt_line/__init__.py
kt_line/cli.py
kt_line/kt_line.py
kt_line-0.3.1.dist-info/entry_points.txt
kt_line-0.3.1.dist-info/LICENSE
kt_line-0.3.1.dist-info/WHEEL
kt_line-0.3.1.dist-info/METADATA
kt_line-0.3.1.dist-info/RECORD
